radical.cm-0.1-py3.9-nspkg.pth
radical/cm/SDIST
radical/cm/VERSION
radical/cm/__init__.py
radical/cm/radical.cm-0.1-b6c3b1ba-master.tar.gz
radical/cm/bookkeeper/__init__.py
radical/cm/bookkeeper/bookkeeper.py
radical/cm/enactor/__init__.py
radical/cm/enactor/base.py
radical/cm/enactor/simulated_enactor.py
radical/cm/planner/__init__.py
radical/cm/planner/base.py
radical/cm/planner/ga_planner.py
radical/cm/planner/heft_planner.py
radical/cm/planner/l2ff_planner.py
radical/cm/planner/random_planner.py
radical/cm/utils/__init__.py
radical/cm/utils/states.py
radical/cm/utils/calculator/__init__.py
radical/cm/utils/calculator/exceptions.py
radical/cm/utils/calculator/api/__init__.py
radical/cm/utils/calculator/api/resource.py
radical/cm/utils/calculator/entities/__init__.py
radical/cm/utils/calculator/entities/core.py
radical/cm/utils/calculator/entities/task.py
radical.cm-0.1.dist-info/LICENSE
radical.cm-0.1.dist-info/METADATA
radical.cm-0.1.dist-info/WHEEL
radical.cm-0.1.dist-info/namespace_packages.txt
radical.cm-0.1.dist-info/top_level.txt
radical.cm-0.1.dist-info/RECORD
