Metadata-Version: 2.1
Name: radical.cm
Version: 0.1
Summary: A campaign manager to execute computational campaign on HPC resources
Home-page: https://www.github.com/iparask/campaign_manager/
Author: Ioannis Paraskevakos
Author-email: g.paraskev@rutgers.edu
License: MIT
Platform: UNKNOWN
Classifier: Development Status :: 1 - Planning
Classifier: Intended Audience :: Developers
Classifier: Environment :: Console
Classifier: Programming Language :: Python
Classifier: Programming Language :: Python :: 3
Classifier: Programming Language :: Python :: 3.7
Classifier: Topic :: Utilities
Classifier: Topic :: System :: Distributed Computing
Classifier: Topic :: Scientific/Engineering
Classifier: Operating System :: MacOS :: MacOS X
Classifier: Operating System :: POSIX
Classifier: Operating System :: Unix
Requires-Dist: radical.entk (==1.0.0)
Requires-Dist: simpy
Requires-Dist: numpy
